cs_gamestate/__init__.py
cs_gamestate/config.py
cs_gamestate/endpoint.py
cs_gamestate/enums/__init__.py
cs_gamestate/enums/bomb.py
cs_gamestate/enums/equipment.py
cs_gamestate/enums/map.py
cs_gamestate/enums/phase.py
cs_gamestate/enums/player.py
cs_gamestate/enums/round.py
cs_gamestate/enums/team.py
cs_gamestate/structs/__init__.py
cs_gamestate/structs/bomb.py
cs_gamestate/structs/equipment.py
cs_gamestate/structs/gamestate.py
cs_gamestate/structs/map.py
cs_gamestate/structs/phase.py
cs_gamestate/structs/player.py
cs_gamestate/structs/provider.py
cs_gamestate/structs/round.py
cs_gamestate/structs/utils.py
cs_gamestate/structs/verify.py
cs_gamestate/utils/__init__.py
cs_gamestate/utils/logger.py
cs_gamestate/utils/make_config.py
cs_gamestate/views/__init__.py
cs_gamestate/views/scoreboard.py
cs_gamestate-0.0.3.dist-info/LICENSE
cs_gamestate-0.0.3.dist-info/METADATA
cs_gamestate-0.0.3.dist-info/WHEEL
cs_gamestate-0.0.3.dist-info/top_level.txt
cs_gamestate-0.0.3.dist-info/RECORD
