Metadata-Version: 2.1
Name: cs-gamestate
Version: 0.0.3
Summary: Counter-Strike Game State Integration for Python
Home-page: https://github.com/iksnagreb/cs-gamestate
Author: Christoph Berganski
License: MIT
Classifier: License :: OSI Approved :: MIT License
Classifier: Programming Language :: Python :: 3
Classifier: Operating System :: POSIX :: Linux
License-File: LICENSE
Requires-Dist: Flask ~=3.0.0
Requires-Dist: pandas ~=2.1.4
Requires-Dist: tabulate ~=0.9.0
